Workbook

Sheet Данные
A1: Дата заказа | B1: Страна | C1: Город | D1: Широта | E1: Долгота | F1: Регион | G1: Код товара | H1: Категория | I1: Подкатегория | J1: Цена за единицу, USD | K1: Себестоимость за единицу, USD | L1: Количество проданных единиц | M1: Выручка, USD | N1: Скидка | O1: Выручка после учета скидки, USD
A2: 44197 | B2: Соединенные Штаты | C2: Лос-Анджелес | D2: =VLOOKUP(C2,координаты!$A$1:$C$656,2,FALSE) -> 34.05 | E2: =VLOOKUP(C2,координаты!$A$1:$C$656,3,FALSE) -> -118.24 | F2: Западный | G2: OFF-ST-10003479 | H2: Одежда | I2: Топы | J2: 40 | K2: 21 | L2: 16 | M2: =J2*L2 -> 640 | N2: 0 | O2: =M2*(1-N2) -> 640
A3: 44197 | B3: Соединенные Штаты | C3: Джексон | D3: =VLOOKUP(C3,координаты!$A$1:$C$656,2,FALSE) -> 32.3 | E3: =VLOOKUP(C3,координаты!$A$1:$C$656,3,FALSE) -> -90.18 | F3: Центральный | G3: OFF-PA-10004675 | H3: Одежда | I3: Деловые костюмы | J3: 400 | K3: 257 | L3: 56 | M3: =J3*L3 -> 22400 | N3: 0.1 | O3: =M3*(1-N3) -> 20160
A4: 44531 | B4: Соединенные Штаты | C4: Мельбурн | D4: =VLOOKUP(C4,координаты!$A$1:$C$656,2,FALSE) -> 28.08 | E4: =VLOOKUP(C4,координаты!$A$1:$C$656,3,FALSE) -> -80.61 | F4: Северный | G4: OFF-ST-10003282 | H4: Одежда | I4: Топы | J4: 41 | K4: 18 | L4: 16 | M4: =J4*L4 -> 656 | N4: 0.2 | O4: =M4*(1-N4) -> 524.8
A5: 44531 | B5: Соединенные Штаты | C5: Лос-Анджелес | D5: =VLOOKUP(C5,координаты!$A$1:$C$656,2,FALSE) -> 34.05 | E5: =VLOOKUP(C5,координаты!$A$1:$C$656,3,FALSE) -> -118.24 | F5: Западный | G5: FUR-FU-10000397 | H5: Обувь | I5: Кроссовки | J5: 32 | K5: 14 | L5: 24 | M5: =J5*L5 -> 768 | N5: 0.2 | O5: =M5*(1-N5) -> 614.4
A6: 44531 | B6: Соединенные Штаты | C6: Хьюстон | D6: =VLOOKUP(C6,координаты!$A$1:$C$656,2,FALSE) -> 29.76 | E6: =VLOOKUP(C6,координаты!$A$1:$C$656,3,FALSE) -> -95.36 | F6: Центральный | G6: TEC-PH-10000486 | H6: Аксессуары | I6: Сумки | J6: 58 | K6: 24 | L6: 32 | M6: =J6*L6 -> 1856 | N6: 0.2 | O6: =M6*(1-N6) -> 1484.8
A7: 44531 | B7: Соединенные Штаты | C7: Сан-Франциско | D7: =VLOOKUP(C7,координаты!$A$1:$C$656,2,FALSE) -> 37.77 | E7: =VLOOKUP(C7,координаты!$A$1:$C$656,3,FALSE) -> -122.42 | F7: Западный | G7: TEC-PH-10001949 | H7: Аксессуары | I7: Сумки | J7: 148 | K7: 61 | L7: 16 | M7: =J7*L7 -> 2368 | N7: 0.2 | O7: =M7*(1-N7) -> 1894.4
A8: 44531 | B8: Соединенные Штаты | C8: Троя | D8: =VLOOKUP(C8,координаты!$A$1:$C$656,2,FALSE) -> 42.61 | E8: =VLOOKUP(C8,координаты!$A$1:$C$656,3,FALSE) -> -83.15 | F8: Северный | G8: OFF-AR-10001868 | H8: Одежда | I8: Куртки | J8: 145 | K8: 68 | L8: 24 | M8: =J8*L8 -> 3480 | N8: 0.2 | O8: =M8*(1-N8) -> 2784
A9: 44531 | B9: Соединенные Штаты | C9: Троя | D9: =VLOOKUP(C9,координаты!$A$1:$C$656,2,FALSE) -> 42.61 | E9: =VLOOKUP(C9,координаты!$A$1:$C$656,3,FALSE) -> -83.15 | F9: Северный | G9: OFF-PA-10001569 | H9: Одежда | I9: Деловые костюмы | J9: 408 | K9: 191 | L9: 24 | M9: =J9*L9 -> 9792 | N9: 0.2 | O9: =M9*(1-N9) -> 7833.6
A10: 44409 | B10: Соединенные Штаты | C10: Хьюстон | D10: =VLOOKUP(C10,координаты!$A$1:$C$656,2,FALSE) -> 29.76 | E10: =VLOOKUP(C10,координаты!$A$1:$C$656,3,FALSE) -> -95.36 | F10: Центральный | G10: FUR-BO-10002545 | H10: Обувь | I10: Шлепки | J10: 31 | K10: 15 | L10: 16 | M10: =J10*L10 -> 496 | N10: 0.2 | O10: =M10*(1-N10) -> 396.8
A11: 44409 | B11: Соединенные Штаты | C11: Сан-Франциско | D11: =VLOOKUP(C11,координаты!$A$1:$C$656,2,FALSE) -> 37.77 | E11: =VLOOKUP(C11,координаты!$A$1:$C$656,3,FALSE) -> -122.42 | F11: Западный | G11: OFF-BI-10001721 | H11: Одежда | I11: Платья | J11: 62 | K11: 29 | L11: 24 | M11: =J11*L11 -> 1488 | N11: 0.2 | O11: =M11*(1-N11) -> 1190.4
A12: 44409 | B12: Соединенные Штаты | C12: Сан-Франциско | D12: =VLOOKUP(C12,координаты!$A$1:$C$656,2,FALSE) -> 37.77 | E12: =VLOOKUP(C12,координаты!$A$1:$C$656,3,FALSE) -> -122.42 | F12: Западный | G12: OFF-BI-10002215 | H12: Одежда | I12: Платья | J12: 80 | K12: 38 | L12: 32 | M12: =J12*L12 -> 2560 | N12: 0.2 | O12: =M12*(1-N12) -> 2048
A13: 44256 | B13: Соединенные Штаты | C13: Уотерфорд | D13: =VLOOKUP(C13,координаты!$A$1:$C$656,2,FALSE) -> 42.69 | E13: =VLOOKUP(C13,координаты!$A$1:$C$656,3,FALSE) -> -83.41 | F13: Центральный | G13: OFF-ST-10001713 | H13: Одежда | I13: Топы | J13: 47 | K13: 18 | L13: 32 | M13: =J13*L13 -> 1504 | N13: 0 | O13: =M13*(1-N13) -> 1504
... A95: 44540 | B95: Соединенные Штаты | C95: Сан-Франциско | D95: =VLOOKUP(C95,координаты!$A$1:$C$656,2,FALSE) -> 37.77 | E95: =VLOOKUP(C95,координаты!$A$1:$C$656,3,FALSE) -> -122.42 | F95: Западный | G95: OFF-AR-10002053 | H95: Одежда | I95: Куртки | J95: 94 | K95: 33 | L95: 8 | M95: =J95*L95 -> 752 | N95: 0.2 | O95: =M95*(1-N95) -> 601.6

Sheet Штаты
A1: Город | B1: Штат
A2: Декейтер | B2: Алабама
A3: Гилберт | B3: Аризона
A4: Сиэтл | B4: Вашингтон
A5: Спрингфилд | B5: Вирджиния
A6: Мадисон | B6: Висконсин
A7: Довер | B7: Делавэр
A8: Чикаго | B8: Иллинойс
A9: Олбани | B9: Индиана
A10: Сан-Франциско | B10: Калифорния
A11: Лос-Анджелес | B11: Калифорния
A12: Хендерсон | B12: Кентукки
... A33: Орем | B33: Юта

Sheet координаты
A1: Вашингтон | B1: 38.9 | C1: -77.04
A2: Абилин | B2: 32.45 | C2: -99.73
A3: Аврора | B3: 41.76 | C3: -88.32
A4: Айдахо-Фолс | B4: 43.47 | C4: -112.03
A5: Айова-Сити | B5: 41.66 | C5: -91.53
A6: Акрон | B6: 41.08 | C6: -81.52
A7: Аламида | B7: 37.77 | C7: -122.24
A8: Александрия | B8: 38.8 | C8: -77.05
A9: Аллен | B9: 33.1 | C9: -96.67
A10: Аллентаун | B10: 40.61 | C10: -75.49
A11: Альбукерке | B11: 35.08 | C11: -106.65
A12: Альгамбра | B12: 34.1 | C12: -118.13
... A656: Янгстаун | B656: 41.1 | C656: -80.65
